BMIPracticeTest/bmi.py
BMIPracticeTest-0.0.0.1.dist-info/METADATA
BMIPracticeTest-0.0.0.1.dist-info/WHEEL
BMIPracticeTest-0.0.0.1.dist-info/top_level.txt
BMIPracticeTest-0.0.0.1.dist-info/RECORD
