Metadata-Version: 2.1
Name: BMIPracticeTest
Version: 0.0.0.1
Summary: Calculate BMI Test Package
Home-page: https://lingua.blog.me/...
Author: Jaeeun Kim
Author-email: kwh@gmail.com
License: MIT
Platform: UNKNOWN
Requires-Python: >=3
